accentnotifications/__init__.py
accentnotifications/manager.py
accentnotifications/types.py
accentnotifications/notifications/__init__.py
accentnotifications/notifications/base.py
accentnotifications/notifications/smtp.py
accentnotifications/notifications/twilio_sms.py
accentnotifications-0.0.18.dist-info/METADATA
accentnotifications-0.0.18.dist-info/WHEEL
accentnotifications-0.0.18.dist-info/licenses/LICENSE
accentnotifications-0.0.18.dist-info/RECORD
