Metadata-Version: 2.4
Name: accentnotifications
Version: 0.0.18
Dynamic: Summary
Project-URL: Homepage, https://github.com/accentdesign/accentnotifications
Author-email: Accent Design Group Ltd <support@accentdesign.co.uk>
License: The MIT License (MIT)
License-File: LICENSE
Classifier: License :: OSI Approved :: MIT License
Classifier: Programming Language :: Python
Classifier: Programming Language :: Python :: 3
Requires-Python: >=3.9
Requires-Dist: pydantic-settings<2.9.0,>=2.0.1
Requires-Dist: pydantic<2.12.0,>=2.0.1
Provides-Extra: smtp
Requires-Dist: aiosmtplib; extra == 'smtp'
Provides-Extra: test
Requires-Dist: pytest; extra == 'test'
Requires-Dist: pytest-asyncio; extra == 'test'
Requires-Dist: pytest-mock; extra == 'test'
Requires-Dist: ruff; extra == 'test'
Provides-Extra: twiliosms
Requires-Dist: aiohttp; extra == 'twiliosms'
